setup.py
ani_probablity/Binomialdistribution.py
ani_probablity/Gaussiandistribution.py
ani_probablity/Generaldistribution.py
ani_probablity/__init__.py
ani_probablity.egg-info/PKG-INFO
ani_probablity.egg-info/SOURCES.txt
ani_probablity.egg-info/dependency_links.txt
ani_probablity.egg-info/not-zip-safe
ani_probablity.egg-info/top_level.txt