Metadata-Version: 1.0
Name: ani-probablity
Version: 0.1
Summary: Gaussian and Binomial distributions
Home-page: UNKNOWN
Author: Anirudh singh sanger
Author-email: UNKNOWN
License: UNKNOWN
Platform: UNKNOWN
